numeros_lotofacil/__init__.py
numeros_lotofacil/sorteio.py
numeros_lotofacil-0.0.1.dist-info/METADATA
numeros_lotofacil-0.0.1.dist-info/WHEEL
numeros_lotofacil-0.0.1.dist-info/top_level.txt
numeros_lotofacil-0.0.1.dist-info/RECORD
