Metadata-Version: 2.1
Name: numeros_lotofacil
Version: 0.0.1
Summary: Sorteia numeros da lotofacil
Home-page: https://github.com/MendesTatah
Author: Thais Mendes
Author-email: thaisppmendes@hotmail.com
Requires-Python: >=3.8
